rl_simple/__init__.py
rl_simple/rl_functions.py
rl_simple_teerth-0.1.0.dist-info/licenses/LICENSE
rl_simple_teerth-0.1.0.dist-info/METADATA
rl_simple_teerth-0.1.0.dist-info/WHEEL
rl_simple_teerth-0.1.0.dist-info/top_level.txt
rl_simple_teerth-0.1.0.dist-info/RECORD
