Metadata-Version: 2.4
Name: rl_simple_teerth
Version: 0.1.0
Summary: Simple RL utilities for epsilon-greedy and TD error
Author: Teerth
Author-email: teerth.chauhan75@nmims.in
Classifier: Programming Language :: Python :: 3
Classifier: License :: OSI Approved :: MIT License
Classifier: Operating System :: OS Independent
Requires-Python: >=3.6
License-File: LICENSE
Dynamic: author
Dynamic: author-email
Dynamic: classifier
Dynamic: description
Dynamic: description-content-type
Dynamic: license-file
Dynamic: requires-python
Dynamic: summary
